examples/__init__.py
examples/kalman_filter_plotting.py
veroku/__init__.py
veroku/_constants.py
veroku/cluster_graph.py
veroku/_cg_helpers/__init__.py
veroku/_cg_helpers/_animation.py
veroku/_cg_helpers/_cluster.py
veroku/factors/__init__.py
veroku/factors/_factor.py
veroku/factors/_factor_template.py
veroku/factors/_factor_utils.py
veroku/factors/_sigma_points.py
veroku/factors/categorical.py
veroku/factors/gaussian.py
veroku/factors/sparse_categorical.py
veroku/factors/experimental/__init__.py
veroku/factors/experimental/factorised_factor.py
veroku/factors/experimental/gaussian_mixture.py
veroku/factors/experimental/nonlinear_gaussian.py
veroku/tests/__init__.py
veroku/tests/integration/__init__.py
veroku/tests/integration/test_notebooks.py
veroku/tests/unit/__init__.py
veroku/tests/unit/test__animation.py
veroku/tests/unit/test__cluster.py
veroku/tests/unit/test__factor_utils.py
veroku/tests/unit/test__sigma_points.py
veroku/tests/unit/test_categorical.py
veroku/tests/unit/test_cluster_graph.py
veroku/tests/unit/test_factorised_factor.py
veroku/tests/unit/test_gaussian.py
veroku/tests/unit/test_gaussian_mixture.py
veroku/tests/unit/test_nonlinear_gaussian.py
veroku-1.0.171.dist-info/LICENSE
veroku-1.0.171.dist-info/METADATA
veroku-1.0.171.dist-info/WHEEL
veroku-1.0.171.dist-info/top_level.txt
veroku-1.0.171.dist-info/RECORD
