Metadata-Version: 2.1
Name: veroku
Version: 1.0.171
Summary: An open source library for building and performing inference with probabilistic graphical models.
Home-page: https://github.com/ejlouw/veroku
Author: EJ Louw
Author-email: ejlouw00@gmail.com
License: BSD 3-Clause License
Platform: UNKNOWN
Classifier: Programming Language :: Python :: 3
Classifier: License :: OSI Approved :: BSD License
Classifier: Operating System :: OS Independent
Requires-Python: >=3.6
License-File: LICENSE
Requires-Dist: matplotlib (<4.0.0,>=3.3.3)
Requires-Dist: seaborn (<1.0.0,>=0.11.0)
Requires-Dist: graphviz (<1.0.0,>=0.10.1)
Requires-Dist: Pillow (<10.0.0,>=9.0.1)
Requires-Dist: ipython (<8.0.0,>=7.5.0)
Requires-Dist: pandas (<2.0.0,>=1.1.3)
Requires-Dist: tqdm (<5.0.0,>=4.48.1)
Requires-Dist: ipympl (<1.0.0,>=0.5.8)
Requires-Dist: numpy (<2.0.0,>=1.19.2)
Requires-Dist: networkx (<3.0,>=2.5)
Requires-Dist: numdifftools (<1.0.0,>=0.9.20)
Requires-Dist: scipy (<2.0.0,>=1.5.2)
